{
    "clients": [
        {
            "id": 1,
            "name": "Roger Pigeon",
            "numberClient": "123456789",
            "address": "12 rue Pigeon, 75000 Paris",
            "Account": {
                "id": 1,
                "balance": 1000.00,
                "numberCompte": "13214215"
            }
        },
        {
            "id": 2,
            "name": "Alice Dupont",
            "numberClient": "987654321",
            "address": "34 avenue des Champs, 75000 Paris",
            "Account": {
                "id": 2,
                "balance": 1500.00,
                "numberCompte": "98765432"
            }
        },
        {
            "id": 3,
            "name": "Jean Valjean",
            "numberClient": "456789123",
            "address": "56 boulevard Victor Hugo, 75000 Paris",
            "Account": {
                "id": 3,
                "balance": 2000.00,
                "numberCompte": "45678912"
            }
        }
    ]
}